dailycalc/__init__.py
dailycalc/__main__.py
dailycalc/icalculator.py
dailycalc/queueregister.py
dailycalc/calculator/__init__.py
dailycalc/calculator/calculator.py
dailycalc/calculator/debug.py
dailycalc/calculator/define.py
dailycalc/calculator/parserlogger.py
dailycalc/calculator/testing.py
dailycalc/calculator/words.py
dailycalc-2024.0.1.1.dist-info/METADATA
dailycalc-2024.0.1.1.dist-info/WHEEL
dailycalc-2024.0.1.1.dist-info/entry_points.txt
dailycalc-2024.0.1.1.dist-info/licenses/LICENSE
dailycalc-2024.0.1.1.dist-info/RECORD
