Metadata-Version: 2.3
Name: dailycalc
Version: 2024.0.1.1
Summary: A simple calcaultor for daily usage
Project-URL: Homepage, https://github.com/quxiaowei/simple-calculator
Project-URL: Issues, https://github.com/quxiaowei/simple-calculator/issues
Author-email: Qu Xiaowei <quxw.work@gmail.com>
License: Copyright (c) 2018 The Python Packaging Authority
License-File: LICENSE
Classifier: License :: OSI Approved :: MIT License
Classifier: Operating System :: OS Independent
Classifier: Programming Language :: Python :: 3
Requires-Python: >=3.11
Requires-Dist: colorama>=0.4.6
